examples/__init__.py
lmdeploy/__init__.py
lmdeploy/__main__.py
lmdeploy/api.py
lmdeploy/archs.py
lmdeploy/logger.py
lmdeploy/messages.py
lmdeploy/model.py
lmdeploy/profiler.py
lmdeploy/tokenizer.py
lmdeploy/utils.py
lmdeploy/version.py
lmdeploy/cli/__init__.py
lmdeploy/cli/cli.py
lmdeploy/cli/entrypoint.py
lmdeploy/cli/lite.py
lmdeploy/cli/serve.py
lmdeploy/cli/utils.py
lmdeploy/lite/__init__.py
lmdeploy/lite/defaults.py
lmdeploy/lite/apis/__init__.py
lmdeploy/lite/apis/auto_awq.py
lmdeploy/lite/apis/calibrate.py
lmdeploy/lite/apis/get_small_sharded_hf.py
lmdeploy/lite/apis/gptq.py
lmdeploy/lite/apis/kv_qparams.py
lmdeploy/lite/apis/smooth_quant.py
lmdeploy/lite/modeling/__init__.py
lmdeploy/lite/modeling/internlm2_gptq.py
lmdeploy/lite/modeling/internlm3_gptq.py
lmdeploy/lite/quantization/__init__.py
lmdeploy/lite/quantization/awq.py
lmdeploy/lite/quantization/calibration.py
lmdeploy/lite/quantization/activation/__init__.py
lmdeploy/lite/quantization/activation/observer.py
lmdeploy/lite/quantization/modules/__init__.py
lmdeploy/lite/quantization/modules/linear.py
lmdeploy/lite/quantization/weight/__init__.py
lmdeploy/lite/quantization/weight/quantizer.py
lmdeploy/lite/utils/__init__.py
lmdeploy/lite/utils/batch_split.py
lmdeploy/lite/utils/cal_qparams.py
lmdeploy/lite/utils/calib_dataloader.py
lmdeploy/lite/utils/collect.py
lmdeploy/lite/utils/global_avail.py
lmdeploy/lite/utils/load.py
lmdeploy/lite/utils/memory_efficient.py
lmdeploy/pytorch/__init__.py
lmdeploy/pytorch/accel.py
lmdeploy/pytorch/block.py
lmdeploy/pytorch/chat.py
lmdeploy/pytorch/config.py
lmdeploy/pytorch/distributed.py
lmdeploy/pytorch/messages.py
lmdeploy/pytorch/model_inputs.py
lmdeploy/pytorch/passkey_retrieval.py
lmdeploy/pytorch/supported_models.py
lmdeploy/pytorch/utils.py
lmdeploy/pytorch/adapter/__init__.py
lmdeploy/pytorch/adapter/adapter.py
lmdeploy/pytorch/backends/__init__.py
lmdeploy/pytorch/backends/activation.py
lmdeploy/pytorch/backends/apply_rotary_emb.py
lazyllm_lmdeploy-0.7.1rc0.dist-info/LICENSE
lazyllm_lmdeploy-0.7.1rc0.dist-info/METADATA
lazyllm_lmdeploy-0.7.1rc0.dist-info/WHEEL
lazyllm_lmdeploy-0.7.1rc0.dist-info/entry_points.txt
lazyllm_lmdeploy-0.7.1rc0.dist-info/top_level.txt
lazyllm_lmdeploy-0.7.1rc0.dist-info/RECORD
