Metadata-Version: 2.1
Name: lazyllm-lmdeploy
Version: 0.7.1rc0
Summary: A toolset for compressing, deploying and serving LLM
Author: OpenMMLab
Author-email: openmmlab@gmail.com
Classifier: Programming Language :: Python :: 3.8
Classifier: Programming Language :: Python :: 3.9
Classifier: Programming Language :: Python :: 3.10
Classifier: Programming Language :: Python :: 3.11
Classifier: Programming Language :: Python :: 3.12
Classifier: Intended Audience :: Developers
Classifier: Intended Audience :: Education
Classifier: Intended Audience :: Science/Research
License-File: LICENSE
Requires-Dist: accelerate >=0.29.3
Requires-Dist: einops
Requires-Dist: fastapi
Requires-Dist: fire
Requires-Dist: mmengine-lite
Requires-Dist: numpy <2.0.0
Requires-Dist: openai
Requires-Dist: outlines
Requires-Dist: peft <=0.14.0
Requires-Dist: pillow
Requires-Dist: protobuf
Requires-Dist: pydantic >2.0.0
Requires-Dist: safetensors
Requires-Dist: sentencepiece
Requires-Dist: shortuuid
Requires-Dist: tiktoken
Requires-Dist: torch <=2.5.1,>=2.0.0
Requires-Dist: torchvision <=0.20.1,>=0.15.0
Requires-Dist: transformers
Requires-Dist: uvicorn
Requires-Dist: triton <=3.1.0,>=3.0.0 ; sys_platform == "linux"
Provides-Extra: all
Requires-Dist: accelerate ; extra == 'all'
Requires-Dist: accelerate >=0.29.3 ; extra == 'all'
Requires-Dist: datasets ; extra == 'all'
Requires-Dist: einops ; extra == 'all'
Requires-Dist: fastapi ; extra == 'all'
Requires-Dist: fire ; extra == 'all'
Requires-Dist: gradio ; extra == 'all'
Requires-Dist: mmengine-lite ; extra == 'all'
Requires-Dist: numpy <2.0.0 ; extra == 'all'
Requires-Dist: openai ; extra == 'all'
Requires-Dist: outlines ; extra == 'all'
Requires-Dist: peft <=0.14.0 ; extra == 'all'
Requires-Dist: pillow ; extra == 'all'
Requires-Dist: protobuf ; extra == 'all'
Requires-Dist: pybind11 <=2.13.1 ; extra == 'all'
Requires-Dist: pydantic >2.0.0 ; extra == 'all'
Requires-Dist: safetensors ; extra == 'all'
Requires-Dist: sentencepiece ; extra == 'all'
Requires-Dist: setuptools ; extra == 'all'
Requires-Dist: shortuuid ; extra == 'all'
Requires-Dist: tiktoken ; extra == 'all'
Requires-Dist: torch <=2.5.1,>=2.0.0 ; extra == 'all'
Requires-Dist: torchvision <=0.20.1,>=0.15.0 ; extra == 'all'
Requires-Dist: transformers ; extra == 'all'
Requires-Dist: transformers-stream-generator ; extra == 'all'
Requires-Dist: tritonclient[grpc] ; extra == 'all'
Requires-Dist: uvicorn ; extra == 'all'
Requires-Dist: triton <=3.1.0,>=3.0.0 ; (sys_platform == "linux") and extra == 'all'
Provides-Extra: lite
Requires-Dist: accelerate ; extra == 'lite'
Requires-Dist: datasets ; extra == 'lite'
Requires-Dist: transformers-stream-generator ; extra == 'lite'
Provides-Extra: serve
Requires-Dist: gradio ; extra == 'serve'
Requires-Dist: protobuf ; extra == 'serve'
Requires-Dist: tritonclient[grpc] ; extra == 'serve'
